sweetdebug/__init__.py
sweetdebug/cli.py
sweetdebug/dm.py
sweetdebug/timer.py
sweetdebug/variable.py
sweetdebug-1.1.1.dist-info/METADATA
sweetdebug-1.1.1.dist-info/WHEEL
sweetdebug-1.1.1.dist-info/entry_points.txt
sweetdebug-1.1.1.dist-info/top_level.txt
sweetdebug-1.1.1.dist-info/RECORD
