Metadata-Version: 2.4
Name: sweetdebug
Version: 1.1.1
Summary: Automatic pdb invoker
Home-page: https://github.com/sweetcocoa/sweetdebug
Author: sweetcocoa
Author-email: sweetcocoa@snu.ac.kr
License: MIT
Requires-Python: >=3
Requires-Dist: backtrace
Provides-Extra: telegram
Requires-Dist: python-telegram-bot; extra == "telegram"
Dynamic: author
Dynamic: author-email
Dynamic: description
Dynamic: description-content-type
Dynamic: home-page
Dynamic: license
Dynamic: provides-extra
Dynamic: requires-dist
Dynamic: requires-python
Dynamic: summary
